MANIFEST.in
README.rst
setup.py
blanc_basic_podcast/__init__.py
blanc_basic_podcast/admin.py
blanc_basic_podcast/apps.py
blanc_basic_podcast/feeds.py
blanc_basic_podcast/itunesfeed.py
blanc_basic_podcast/models.py
blanc_basic_podcast/tests.py
blanc_basic_podcast/urls.py
blanc_basic_podcast/utils.py
blanc_basic_podcast/validators.py
blanc_basic_podcast/views.py
blanc_basic_podcast.egg-info/PKG-INFO
blanc_basic_podcast.egg-info/SOURCES.txt
blanc_basic_podcast.egg-info/dependency_links.txt
blanc_basic_podcast.egg-info/requires.txt
blanc_basic_podcast.egg-info/top_level.txt
blanc_basic_podcast/migrations/0001_initial.py
blanc_basic_podcast/migrations/0002_podcastfile_date_url.py
blanc_basic_podcast/migrations/0003_populate_date_url.py
blanc_basic_podcast/migrations/0004_date_url_required.py
blanc_basic_podcast/migrations/0005_podcastfile_file_size.py
blanc_basic_podcast/migrations/0006_populate_file_size.py
blanc_basic_podcast/migrations/__init__.py